{
  "items": [
    {
      "title": "엄마의심부름 <b>보드게임</b> 117종 음식카드 스피드 가족 파티 수학교구 어린이 초등학생 장난감",
      "link": "https://smartstore.naver.com/main/products/11810917604",
      "image": "https://shopping-phinf.pstatic.net/main_8935542/89355428191.jpg",
      "lprice": "27900",
      "hprice": "",
      "mallName": "한결같이 보드게임",
      "productId": "89355428191",
      "productType": "2",
      "brand": "한결같이",
      "maker": "",
      "category1": "생활/건강",
      "category2": "수집품",
      "category3": "게임",
      "category4": "보드게임"
    },
    {
      "title": "도블 크리스마스 어린이 캠핑 그림 <b>보드게임</b>",
      "link": "https://smartstore.naver.com/main/products/11965859903",
      "image": "https://shopping-phinf.pstatic.net/main_8951037/89510370591.jpg",
      "lprice": "5600",
      "hprice": "",
      "mallName": "체바오트",
      "productId": "89510370591",
      "productType": "2",
      "brand": "",
      "maker": "",
      "category1": "생활/건강",
      "category2": "수집품",
      "category3": "게임",
      "category4": "보드게임"
    },
    {
      "title": "코리아<b>보드게임</b>즈 스플렌더 한글판",
      "link": "https://search.shopping.naver.com/catalog/17247202786",
      "image": "https://shopping-phinf.pstatic.net/main_1724720/17247202786.20250630081912.jpg",
      "lprice": "35020",
      "hprice": "",
      "mallName": "네이버",
      "productId": "17247202786",
      "productType": "1",
      "brand": "코리아보드게임즈",
      "maker": "코리아보드게임즈",
      "category1": "생활/건강",
      "category2": "수집품",
      "category3": "게임",
      "category4": "보드게임"
    },
    {
      "title": "[<b>보드게임</b>대여] 3개선택 대여렌탈 페이지",
      "link": "https://smartstore.naver.com/main/products/4920785666",
      "image": "https://shopping-phinf.pstatic.net/main_8246530/82465309580.11.jpg",
      "lprice": "10000",
      "hprice": "",
      "mallName": "보드게임대여 퍼니보드랜드",
      "productId": "82465309580",
      "productType": "2",
      "brand": "",
      "maker": "",
      "category1": "생활/건강",
      "category2": "수집품",
      "category3": "게임",
      "category4": "보드게임"
    },
    {
      "title": "우노 <b>보드게임</b>",
      "link": "https://search.shopping.naver.com/catalog/52101537017",
      "image": "https://shopping-phinf.pstatic.net/main_5210153/52101537017.20241224203810.jpg",
      "lprice": "8630",
      "hprice": "",
      "mallName": "네이버",
      "productId": "52101537017",
      "productType": "1",
      "brand": "",
      "maker": "",
      "category1": "생활/건강",
      "category2": "수집품",
      "category3": "게임",
      "category4": "보드게임"
    },
    {
      "title": "코리아<b>보드게임</b>즈 텔레스트레이션 4 8인용 그림 그리기 연상 텔레파시 동상이몽 파티 추리 퀴즈",
      "link": "https://search.shopping.naver.com/catalog/45740728947",
      "image": "https://shopping-phinf.pstatic.net/main_4574072/45740728947.20250710125012.jpg",
      "lprice": "15130",
      "hprice": "",
      "mallName": "네이버",
      "productId": "45740728947",
      "productType": "1",
      "brand": "코리아보드게임즈",
      "maker": "",
      "category1": "생활/건강",
      "category2": "수집품",
      "category3": "게임",
      "category4": "보드게임"
    },
    {
      "title": "아스모디 엠투월드 <b>보드게임</b> 꼬치의달인 파티게임",
      "link": "https://search.shopping.naver.com/catalog/49018064543",
      "image": "https://shopping-phinf.pstatic.net/main_4901806/49018064543.20250326025233.jpg",
      "lprice": "28000",
      "hprice": "",
      "mallName": "네이버",
      "productId": "49018064543",
      "productType": "1",
      "brand": "아스모디",
      "maker": "",
      "category1": "생활/건강",
      "category2": "수집품",
      "category3": "게임",
      "category4": "보드게임"
    },
    {
      "title": "스플렌더 <b>보드게임</b> 캠핑 초등학생 어린이날 선물",
      "link": "https://smartstore.naver.com/main/products/7987414878",
      "image": "https://shopping-phinf.pstatic.net/main_8553191/85531915201.3.jpg",
      "lprice": "20000",
      "hprice": "",
      "mallName": "체바오트",
      "productId": "85531915201",
      "productType": "2",
      "brand": "",
      "maker": "",
      "category1": "생활/건강",
      "category2": "수집품",
      "category3": "게임",
      "category4": "보드게임"
    },
    {
      "title": "코리아<b>보드게임</b>즈 할리갈리",
      "link": "https://search.shopping.naver.com/catalog/5591547578",
      "image": "https://shopping-phinf.pstatic.net/main_5591547/5591547578.20210420091459.jpg",
      "lprice": "11900",
      "hprice": "",
      "mallName": "네이버",
      "productId": "5591547578",
      "productType": "1",
      "brand": "코리아보드게임즈",
      "maker": "코리아보드게임즈",
      "category1": "생활/건강",
      "category2": "수집품",
      "category3": "게임",
      "category4": "보드게임"
    },
    {
      "title": "코리아<b>보드게임</b>즈 우봉고",
      "link": "https://search.shopping.naver.com/catalog/6712875893",
      "image": "https://shopping-phinf.pstatic.net/main_6712875/6712875893.20240827150340.jpg",
      "lprice": "35840",
      "hprice": "",
      "mallName": "네이버",
      "productId": "6712875893",
      "productType": "1",
      "brand": "코리아보드게임즈",
      "maker": "코리아보드게임즈",
      "category1": "생활/건강",
      "category2": "수집품",
      "category3": "게임",
      "category4": "보드게임"
    },
    {
      "title": "코리아<b>보드게임</b>즈 사보타지",
      "link": "https://search.shopping.naver.com/catalog/17629682428",
      "image": "https://shopping-phinf.pstatic.net/main_1762968/17629682428.20251020142500.jpg",
      "lprice": "9380",
      "hprice": "",
      "mallName": "네이버",
      "productId": "17629682428",
      "productType": "1",
      "brand": "코리아보드게임즈",
      "maker": "",
      "category1": "생활/건강",
      "category2": "수집품",
      "category3": "게임",
      "category4": "보드게임"
    },
    {
      "title": "코리아<b>보드게임</b>즈 라쿠카라차 <b>보드게임</b>",
      "link": "https://search.shopping.naver.com/catalog/36038503985",
      "image": "https://shopping-phinf.pstatic.net/main_3603850/36038503985.20250415165916.jpg",
      "lprice": "50340",
      "hprice": "",
      "mallName": "네이버",
      "productId": "36038503985",
      "productType": "1",
      "brand": "코리아보드게임즈",
      "maker": "",
      "category1": "생활/건강",
      "category2": "수집품",
      "category3": "게임",
      "category4": "보드게임"
    },
    {
      "title": "씨앗사 부루마블 클래식 58000",
      "link": "https://search.shopping.naver.com/catalog/5655033203",
      "image": "https://shopping-phinf.pstatic.net/main_5655033/5655033203.20191030115803.jpg",
      "lprice": "35300",
      "hprice": "",
      "mallName": "네이버",
      "productId": "5655033203",
      "productType": "1",
      "brand": "씨앗사",
      "maker": "씨앗사",
      "category1": "생활/건강",
      "category2": "수집품",
      "category3": "게임",
      "category4": "보드게임"
    },
    {
      "title": "300pcs 카지노칩 세트 세븐 카드 포커칩 <b>게임</b>칩 홀덤",
      "link": "https://smartstore.naver.com/main/products/232219319",
      "image": "https://shopping-phinf.pstatic.net/main_7726606/7726606633.7.jpg",
      "lprice": "26800",
      "hprice": "",
      "mallName": "이뽀나몰",
      "productId": "7726606633",
      "productType": "2",
      "brand": "",
      "maker": "",
      "category1": "생활/건강",
      "category2": "수집품",
      "category3": "게임",
      "category4": "보드게임"
    },
    {
      "title": "프리미엄 자석 원목 체스 휴대용 고급 체스판 수공예상판 (설명서 퀸2개)소나무체스-중",
      "link": "https://smartstore.naver.com/main/products/10434030998",
      "image": "https://shopping-phinf.pstatic.net/main_8797853/87978536033.1.jpg",
      "lprice": "39800",
      "hprice": "",
      "mallName": "데이닷 DAYDOT",
      "productId": "87978536033",
      "productType": "2",
      "brand": "",
      "maker": "",
      "category1": "생활/건강",
      "category2": "수집품",
      "category3": "게임",
      "category4": "보드게임"
    }
  ]
}